Workbook

Sheet Cover
B2: HP INC. — COMPARABLE COMPANIES ANALYSIS
B5: Target Company: | C5: HP Inc.
B6: Date of Analysis: | C6: July 8, 2026
B7: Market Data As Of: | C7: Jul 7–8, 2026 (see individual sources for exact timestamps)
B9: Contents
B10: Sheet | C10: Task
B11: Task A — Company Overview | C11: Business profile, segments, geography, competitors
B12: Task B — Peer Selection | C12: Comparable company screen with inclusion/exclusion rationale
B13: Task C — Financial Data | C13: Raw financials for target + peer set, sourced
B14: Task D — Trading Multiples | C14: EV/Sales, EV/EBITDA, EV/EBIT, P/E, P/BV, growth, margins, returns, leverage
B15: Task E — Benchmarking | C15: Ranking, median/mean, outlier identification
B16: Task F — Valuation | C16: Implied HP Inc. value — Low / Base / High cases

Sheet A. Company Overview
B2: TASK A - HP INC. BUSINESS PROFILE
B4: Business Model | C4: HP Inc. designs, manufactures, markets, and services personal computing devices and printing systems, monetizing hardware plus a high-margin, recurring supplies/ink-and-toner annuity attached to its installed printer base. Revenue is split between Personal Systems (PCs, notebooks, workstations) and Printing (hardware + supplies), with a small Corporate Investments segment for emerging bets.
B5: Products & Services | C5: Commercial & consumer desktops/notebooks, workstations, thin clients, displays; home/office inkjet & LaserJet printers, 3D printing, and managed print/device-as-a-service offerings; software, security, and lifecycle support services bundled with hardware sales.
B6: Revenue Segments (FY2025) | C6: Personal Systems ~68% of revenue; Printing ~32% of revenue (supplies carry materially higher margins than hardware in both segments). Fiscal 2025 total net revenue was $55.3B, up 3.2% YoY; TTM (Apr-2026) revenue is $57.4B, up 5.7% YoY, aided by AI PC refresh demand.
B7: Geographical Presence | C7: Global operations across the Americas, EMEA, and Asia-Pacific/Japan, with the U.S. as the single largest market. Manufacturing and supply chain are diversified across Asia, with some diversification out of China in recent years to manage tariff exposure.
B8: Industry Overview | C8: HP competes in mature, low-growth PC and printing hardware markets characterized by thin single-digit operating margins, commoditized components, and periodic replacement cycles (e.g., Windows refresh, AI-PC upgrade waves). Growth is now driven more by mix-shift (premium/AI PCs, commercial contracts) than unit volume.
B9: Major Competitors | C9: PCs: Dell Technologies, Lenovo Group, Apple, ASUS, Acer. Printing: Canon, Seiko Epson, Brother Industries, Xerox Holdings (post-Lexmark). HP is the #1 or #2 global player by unit share in both PCs and printers depending on the quarter and geography.
B10: Recent Strategic Developments | C10: FY2025 GAAP diluted EPS of $2.65 (down from $2.81) reflects margin pressure from input costs, offset partly by a $1.9B 'Future Ready' cost-savings program. HP announced a strategic AI partnership with OpenAI (June 2026) and continues to expand its AI PC portfolio (NVIDIA RTX Spark-powered devices) to defend PC segment share and margin.
B12: Sources: HP Inc. FY2025 10-K and Q4 FY25 earnings release (investor.hp.com, Nov 25 2025); .
B14: FY2025 Revenue Mix (illustrative)
B15: Segment | C15: Revenue ($B)
B16: Personal Systems | C16: 37.6
B17: Printing | C17: 17.7

Sheet B. Peer Selection
B2: TASK B - COMPARABLE COMPANY SCREEN
B4: Company | C4: Ticker | D4: Included / Excluded | E4: Reason | F4: Industry Fit | G4: Business Model Fit
B5: Dell Technologies Inc. | C5: DELL | D5: Included | E5: Direct PC/workstation competitor; comparable commercial hardware mix; similar low-margin, high-volume model though increasingly levered to AI servers. | F5: High | G5: High
B6: Lenovo Group Ltd. | C6: LNVGY | D6: Included | E6: World's #1 PC OEM by unit share; near-identical Personal Systems business model and customer base to HP. | F6: High | G6: High
B7: Canon Inc. | C7: CAJ | D7: Included | E7: Leading printer/imaging OEM; hardware + high-margin consumables model closely mirrors HP's Printing segment. | F7: High | G7: High
B8: Seiko Epson Corp. | C8: 6724.T | D8: Included | E8: Global inkjet printer leader; comparable supplies-driven annuity revenue model to HP Printing. | F8: High | G8: High
B9: Xerox Holdings Corp. | C9: XRX | D9: Included | E9: Direct printing/office-equipment competitor (post-Lexmark); included for range despite distressed financial profile - see outlier flag. | F9: High | G9: Medium
B10: Apple Inc. | C10: AAPL | D10: Excluded | E10: Materially different business model (premium-only, vertically-integrated ecosystem, services-driven margins); market cap ~50x HP's, distorts multiples. | F10: Medium | G10: Low
B11: Hewlett Packard Enterprise | C11: HPE | D11: Excluded | E11: Spun off from HP in 2015 into enterprise servers/networking/hybrid cloud - no meaningful overlap with HP's PC/print business today. | F11: Low | G11: Low
B12: Brother Industries Ltd. | C12: BRTHY | D12: Excluded | E12: Comparable printing model but heavily diversified into machine tools/industrial equipment (~40% of revenue), reducing pure-play comparability; no reliable USD financial feed at time of analysis. | F12: Medium | G12: Medium
B13: ASUSTeK Computer Inc. | C13: 2357.TW | D13: Excluded | E13: PC/motherboard maker but skews consumer/gaming and components distribution; limited commercial enterprise overlap with HP. | F13: Medium | G13: Medium
B15: Final Comparable Set (5 peers): Dell Technologies, Lenovo Group, Canon, Seiko Epson, Xerox Holdings.
B16: Selection Criteria Applied: (i) Industry - PC hardware and/or printing/imaging OEM; (ii) Business Model - hardware sale + recurring supplies/services where applicable; (iii) Company Size - global scale peers (market cap $0.3B-$270B range, reflecting current market dispersion); (iv) Growth Profile - low-to-mid single digit core hardware growth (Dell's AI-server-driven growth is a noted outlier); (v) Profitability - thin single-to-low-double-digit operating margins typical of hardware OEMs; (vi) Geography - global, multi-region revenue base.

Sheet C. Financial Data
B2: TASK C - FINANCIAL DATA (ALL FIGURES IN USD MILLIONS UNLESS NOTED)
B4: Company | C4: Ticker | D4: Period / As-of | E4: Currency | F4: Share Price | G4: Shares Out (M) | H4: Market Cap | I4: Cash & Equiv. | J4: Total Debt | K4: Enterprise Value | L4: Revenue | M4: EBITDA | N4: EBIT | O4: Net Income | P4: Book Equity | Q4: Revenue Growth | R4: Source
B5: HP Inc. (Target) | C5: HPQ | D5: TTM Apr-2026 | E5: USD | F5: 22.99 | G5: 914.52 | H5: =F5*G5 -> 21024.815 | I5: 3703 | J5: 9666 | K5: =H5+J5-I5 -> 26987.815 | L5: 57417 | M5: 4038 | N5: 3046 | O5: 2553 | P5: -144 | Q5: 0.0574 | R5: stockanalysis.com/stocks/hpq, HP FY2025 10-K (SEC), accessed Jul 7-8 2026
B6: Dell Technologies | C6: DELL | D6: TTM May-2026 | E6: USD | F6: 417.28 | G6: 646.14 | H6: =F6*G6 -> 269621.3 | I6: 11578 | J6: 31161 | K6: =H6+J6-I6 -> 289204.3 | L6: 134002 | M6: 13689 | N6: 10640 | O6: 8409 | P6: -1404 | Q6: 0.3857 | R6: stockanalysis.com/stocks/dell, Dell FY2026 10-K (SEC), accessed Jul 7-8 2026
B7: Canon Inc. | C7: CAJ (ADR) | D7: TTM (~Mar-2026) | E7: USD | G7: 924 | H7: 26080 | I7: 4750 | J7: 8150 | K7: =H7+J7-I7 -> 29480 | L7: 30930 | M7: 4730 | N7: 3130 | O7: 1090 | P7: 23210 | Q7: n/a | R7: stockanalysis.com/stocks/cajpy/statistics, accessed Jul 2026 (shares derived: Net Income / EPS)
B8: Xerox Holdings | C8: XRX | D8: TTM (Q1'26) | E8: USD | F8: 2.65 | G8: 130.78 | H8: =F8*G8 -> 346.567 | I8: 3857 | J8: 7720 | K8: =H8+J8-I8 -> 4209.567 | L8: 7410 | M8: 348 | N8: 10 | O8: -1060 | P8: 919 | Q8: 0.1288 | R8: stockanalysis.com/stocks/xrx/statistics, accessed Jul 2026 (Cash, Debt, Equity derived from disclosed ratios: D/E, ROE, EV)
B9: Lenovo Group | C9: LNVGY (ADR) | D9: TTM (~Sep-2025) | E9: USD | G9: 13583 | H9: 14310 | I9: 5240 | J9: 4840 | K9: =H9+J9-I9 -> 13910 | L9: 75060 | M9: 3350 | N9: 2290 | O9: 1630 | P9: 7490 | Q9: 0.2026 | R9: stockanalysis.com/quote/otc/LNVGY/statistics, accessed Jul 2026 (shares derived: Net Income / EPS; growth % from stockanalysis.com FY2026 overview)
B10: Seiko Epson | C10: 6724.T | D10: TTM (~Mar-2026) | E10: JPY->USD | G10: 320.43 | H10: 5568 | I10: 1781 | J10: 1429 | K10: =H10+J10-I10 -> 5216 | L10: 8704 | M10: 784 | N10: 306 | O10: 112 | P10: 5269 | Q10: 0.0369 | R10: stockanalysis.com/quote/tyo/6724/statistics, accessed Jun 18 2026; converted at USD/JPY 162.0 (Fed H.10, early Jul 2026)
B12: Legend:
B13: Blue = hard-coded input (sourced)
B14: Black = formula (calculated within this sheet)

Sheet D. Trading Multiples
B2: TASK D - TRADING MULTIPLES (FORMULAS LINK TO 'C. FINANCIAL DATA')
B4: Company | C4: EV/Sales | D4: EV/EBITDA | E4: EV/EBIT | F4: P/E | G4: P/BV | H4: Revenue Growth | I4: EBITDA Margin | J4: ROE | K4: ROCE | L4: Debt/ Equity
B5: HP Inc. (Target) | C5: ='C. Financial Data'!K5/'C. Financial Data'!L5 -> 0.47003178 | D5: ='C. Financial Data'!K5/'C. Financial Data'!M5 -> 6.6834608 | E5: ='C. Financial Data'!K5/'C. Financial Data'!N5 -> 8.8600837 | F5: =IF('C. Financial Data'!O5<=0,"N/M",'C. Financial Data'!H5/'C. Financial Data'!O5) -> 8.2353368 | G5: =IF('C. Financial Data'!P5<=0,"N/M",'C. Financial Data'!H5/'C. Financial Data'!P5) -> N/M | H5: ='C. Financial Data'!Q5 -> 0.0574 | I5: ='C. Financial Data'!M5/'C. Financial Data'!L5 -> 0.070327603 | J5: =IF('C. Financial Data'!P5<=0,"N/M",'C. Financial Data'!O5/'C. Financial Data'!P5) -> N/M | K5: ='C. Financial Data'!N5/('C. Financial Data'!P5+'C. Financial Data'!J5) -> 0.31989078 | L5: =IF('C. Financial Data'!P5<=0,"N/M",'C. Financial Data'!J5/'C. Financial Data'!P5) -> N/M
B6: Dell Technologies | C6: ='C. Financial Data'!K6/'C. Financial Data'!L6 -> 2.1582088 | D6: ='C. Financial Data'!K6/'C. Financial Data'!M6 -> 21.126766 | E6: ='C. Financial Data'!K6/'C. Financial Data'!N6 -> 27.180855 | F6: =IF('C. Financial Data'!O6<=0,"N/M",'C. Financial Data'!H6/'C. Financial Data'!O6) -> 32.06342 | G6: =IF('C. Financial Data'!P6<=0,"N/M",'C. Financial Data'!H6/'C. Financial Data'!P6) -> N/M | H6: ='C. Financial Data'!Q6 -> 0.3857 | I6: ='C. Financial Data'!M6/'C. Financial Data'!L6 -> 0.10215519 | J6: =IF('C. Financial Data'!P6<=0,"N/M",'C. Financial Data'!O6/'C. Financial Data'!P6) -> N/M | K6: ='C. Financial Data'!N6/('C. Financial Data'!P6+'C. Financial Data'!J6) -> 0.35756293 | L6: =IF('C. Financial Data'!P6<=0,"N/M",'C. Financial Data'!J6/'C. Financial Data'!P6) -> N/M
B7: Canon Inc. | C7: ='C. Financial Data'!K7/'C. Financial Data'!L7 -> 0.95311995 | D7: ='C. Financial Data'!K7/'C. Financial Data'!M7 -> 6.2325581 | E7: ='C. Financial Data'!K7/'C. Financial Data'!N7 -> 9.4185304 | F7: =IF('C. Financial Data'!O7<=0,"N/M",'C. Financial Data'!H7/'C. Financial Data'!O7) -> 23.926606 | G7: =IF('C. Financial Data'!P7<=0,"N/M",'C. Financial Data'!H7/'C. Financial Data'!P7) -> 1.1236536 | H7: ='C. Financial Data'!Q7 -> n/a | I7: ='C. Financial Data'!M7/'C. Financial Data'!L7 -> 0.15292596 | J7: =IF('C. Financial Data'!P7<=0,"N/M",'C. Financial Data'!O7/'C. Financial Data'!P7) -> 0.046962516 | K7: ='C. Financial Data'!N7/('C. Financial Data'!P7+'C. Financial Data'!J7) -> 0.099808673 | L7: =IF('C. Financial Data'!P7<=0,"N/M",'C. Financial Data'!J7/'C. Financial Data'!P7) -> 0.35114175
B8: Xerox Holdings | C8: ='C. Financial Data'!K8/'C. Financial Data'!L8 -> 0.56809271 | D8: ='C. Financial Data'!K8/'C. Financial Data'!M8 -> 12.096457 | E8: ='C. Financial Data'!K8/'C. Financial Data'!N8 -> 420.9567 | F8: =IF('C. Financial Data'!O8<=0,"N/M",'C. Financial Data'!H8/'C. Financial Data'!O8) -> N/M | G8: =IF('C. Financial Data'!P8<=0,"N/M",'C. Financial Data'!H8/'C. Financial Data'!P8) -> 0.37711317 | H8: ='C. Financial Data'!Q8 -> 0.1288 | I8: ='C. Financial Data'!M8/'C. Financial Data'!L8 -> 0.046963563 | J8: =IF('C. Financial Data'!P8<=0,"N/M",'C. Financial Data'!O8/'C. Financial Data'!P8) -> -1.1534276 | K8: ='C. Financial Data'!N8/('C. Financial Data'!P8+'C. Financial Data'!J8) -> 0.0011575414 | L8: =IF('C. Financial Data'!P8<=0,"N/M",'C. Financial Data'!J8/'C. Financial Data'!P8) -> 8.4004353
B9: Lenovo Group | C9: ='C. Financial Data'!K9/'C. Financial Data'!L9 -> 0.18531841 | D9: ='C. Financial Data'!K9/'C. Financial Data'!M9 -> 4.1522388 | E9: ='C. Financial Data'!K9/'C. Financial Data'!N9 -> 6.0742358 | F9: =IF('C. Financial Data'!O9<=0,"N/M",'C. Financial Data'!H9/'C. Financial Data'!O9) -> 8.7791411 | G9: =IF('C. Financial Data'!P9<=0,"N/M",'C. Financial Data'!H9/'C. Financial Data'!P9) -> 1.9105474 | H9: ='C. Financial Data'!Q9 -> 0.2026 | I9: ='C. Financial Data'!M9/'C. Financial Data'!L9 -> 0.044630962 | J9: =IF('C. Financial Data'!P9<=0,"N/M",'C. Financial Data'!O9/'C. Financial Data'!P9) -> 0.2176235 | K9: ='C. Financial Data'!N9/('C. Financial Data'!P9+'C. Financial Data'!J9) -> 0.18572587 | L9: =IF('C. Financial Data'!P9<=0,"N/M",'C. Financial Data'!J9/'C. Financial Data'!P9) -> 0.64619493
B10: Seiko Epson | C10: ='C. Financial Data'!K10/'C. Financial Data'!L10 -> 0.59926471 | D10: ='C. Financial Data'!K10/'C. Financial Data'!M10 -> 6.6530612 | E10: ='C. Financial Data'!K10/'C. Financial Data'!N10 -> 17.045752 | F10: =IF('C. Financial Data'!O10<=0,"N/M",'C. Financial Data'!H10/'C. Financial Data'!O10) -> 49.714286 | G10: =IF('C. Financial Data'!P10<=0,"N/M",'C. Financial Data'!H10/'C. Financial Data'!P10) -> 1.056747 | H10: ='C. Financial Data'!Q10 -> 0.0369 | I10: ='C. Financial Data'!M10/'C. Financial Data'!L10 -> 0.090073529 | J10: =IF('C. Financial Data'!P10<=0,"N/M",'C. Financial Data'!O10/'C. Financial Data'!P10) -> 0.021256405 | K10: ='C. Financial Data'!N10/('C. Financial Data'!P10+'C. Financial Data'!J10) -> 0.045685279 | L10: =IF('C. Financial Data'!P10<=0,"N/M",'C. Financial Data'!J10/'C. Financial Data'!P10) -> 0.27120896
B12: N/M = Not Meaningful (negative earnings, negative or near-zero equity, or a near-zero denominator distorting the ratio).

Sheet E. Benchmarking
B2: TASK E - BENCHMARKING (PEERS ONLY; TARGET EXCLUDED FROM STATS)
B4: Ranking by EV/EBITDA (High to Low)
B5: Rank | C5: Company | D5: EV/Sales | E5: EV/EBITDA | F5: EV/EBIT | G5: P/E
B6: 1 | C6: Dell Technologies | D6: ='D. Trading Multiples'!C6 -> 2.1582088 | E6: ='D. Trading Multiples'!D6 -> 21.126766 | F6: ='D. Trading Multiples'!E6 -> 27.180855 | G6: ='D. Trading Multiples'!F6 -> 32.06342
B7: 2 | C7: Xerox Holdings | D7: ='D. Trading Multiples'!C8 -> 0.56809271 | E7: ='D. Trading Multiples'!D8 -> 12.096457 | F7: ='D. Trading Multiples'!E8 -> 420.9567 | G7: ='D. Trading Multiples'!F8 -> N/M
B8: 3 | C8: Seiko Epson | D8: ='D. Trading Multiples'!C10 -> 0.59926471 | E8: ='D. Trading Multiples'!D10 -> 6.6530612 | F8: ='D. Trading Multiples'!E10 -> 17.045752 | G8: ='D. Trading Multiples'!F10 -> 49.714286
B9: 4 | C9: Canon Inc. | D9: ='D. Trading Multiples'!C7 -> 0.95311995 | E9: ='D. Trading Multiples'!D7 -> 6.2325581 | F9: ='D. Trading Multiples'!E7 -> 9.4185304 | G9: ='D. Trading Multiples'!F7 -> 23.926606
B10: 5 | C10: Lenovo Group | D10: ='D. Trading Multiples'!C9 -> 0.18531841 | E10: ='D. Trading Multiples'!D9 -> 4.1522388 | F10: ='D. Trading Multiples'!E9 -> 6.0742358 | G10: ='D. Trading Multiples'!F9 -> 8.7791411
B12: Summary Statistics - Peer Set (5 comps)
B13: Metric | C13: EV/Sales | D13: EV/EBITDA | E13: EV/EBIT* | F13: P/E*
B14: Median | C14: =MEDIAN('D. Trading Multiples'!C6:C10) -> 0.59926471 | D14: =MEDIAN('D. Trading Multiples'!D6:D10) -> 6.6530612 | E14: =MEDIAN('D. Trading Multiples'!E6:E10) -> 17.045752 | F14: =MEDIAN('D. Trading Multiples'!F6:F10) -> 27.995013
B15: Mean (Average) | C15: =AVERAGE('D. Trading Multiples'!C6:C10) -> 0.89280092 | D15: =AVERAGE('D. Trading Multiples'!D6:D10) -> 10.052216 | E15: =AVERAGE('D. Trading Multiples'!E6:E10) -> 96.135215 | F15: =AVERAGE('D. Trading Multiples'!F6:F10) -> 28.620863
B16: Min | C16: =MIN('D. Trading Multiples'!C6:C10) -> 0.18531841 | D16: =MIN('D. Trading Multiples'!D6:D10) -> 4.1522388 | E16: =MIN('D. Trading Multiples'!E6:E10) -> 6.0742358 | F16: =MIN('D. Trading Multiples'!F6:F10) -> 8.7791411
B17: Max | C17: =MAX('D. Trading Multiples'!C6:C10) -> 2.1582088 | D17: =MAX('D. Trading Multiples'!D6:D10) -> 21.126766 | E17: =MAX('D. Trading Multiples'!E6:E10) -> 420.9567 | F17: =MAX('D. Trading Multiples'!F6:F10) -> 49.714286
B18: Median excl. outliers (core 3)** | C18: =MEDIAN('D. Trading Multiples'!C7,'D. Trading Multiples'!C9,'D. Trading Multiples'!C10) -> 0.59926471 | D18: =MEDIAN('D. Trading Multiples'!D7,'D. Trading Multiples'!D9,'D. Trading Multiples'!D10) -> 6.2325581
B20: * EV/EBIT and P/E medians/means computed only over comps where the ratio is numeric (Xerox's near-zero EBIT and negative earnings are excluded via ISNUMBER filter, not by hardcoding).
B21: ** Core peer set excludes Dell (AI-server-driven re-rating, PE ~33x / EV-EBITDA ~21x - not representative of core PC/print economics) and Xerox (post-merger turnaround with negative equity/earnings - several ratios N/M).
B23: Outlier Identification
B24: Dell Technologies | C24: EV/EBITDA ~21x and P/E ~33x are 2-4x the rest of the peer set, driven by a mid-2026 AI-server-demand re-rating and political commentary (stock +230% over the trailing year) rather than PC/print fundamentals. Retained in the full comp set for disclosure but excluded from the 'core' median used in Task F valuation.
B25: Xerox Holdings | C25: Negative net income, negative/near-zero book equity, and near-zero EBIT make P/E, P/BV, ROE, and EV/EBIT not meaningful (N/M). EV/EBITDA (~12x) is still usable but is elevated versus peers, reflecting the market pricing in execution/leverage risk on a small equity base post-Lexmark. Excluded from the 'core' median.
B26: Canon, Lenovo, Seiko Epson | C26: Form a tight 'core' cluster (EV/EBITDA 4.4x-6.7x; EV/Sales 0.2x-1.0x) viewed as the most representative comparables for HP's mature, hardware+consumables economics.

Sheet F. Valuation
B2: TASK F - IMPLIED VALUATION OF HP INC.
B4: HP Inc. Financial Inputs (linked from Financial Data)
B5: Revenue (TTM, $M) | C5: ='C. Financial Data'!L5 -> 57417
B6: EBITDA (TTM, $M) | C6: ='C. Financial Data'!M5 -> 4038
B7: EBIT (TTM, $M) | C7: ='C. Financial Data'!N5 -> 3046
B8: Net Income (TTM, $M) | C8: ='C. Financial Data'!O5 -> 2553
B9: Total Debt ($M) | C9: ='C. Financial Data'!J5 -> 9666
B10: Cash & Equivalents ($M) | C10: ='C. Financial Data'!I5 -> 3703
B11: Net Debt ($M) | C11: ='C. Financial Data'!J5-'C. Financial Data'!I5 -> 5963
B12: Diluted Shares Out (M) | C12: ='C. Financial Data'!G5 -> 914.52
B13: Current Share Price | C13: ='C. Financial Data'!F5 -> 22.99
B15: Peer Multiple Basis (core 3: Canon, Lenovo, Seiko Epson)
B16: Multiple | C16: Low (Min) | D16: Base (Median) | E16: High (Max)
B17: EV / Sales | C17: =MIN('D. Trading Multiples'!C7,'D. Trading Multiples'!C9,'D. Trading Multiples'!C10) -> 0.18531841 | D17: =MEDIAN('D. Trading Multiples'!C7,'D. Trading Multiples'!C9,'D. Trading Multiples'!C10) -> 0.59926471 | E17: =MAX('D. Trading Multiples'!C7,'D. Trading Multiples'!C9,'D. Trading Multiples'!C10) -> 0.95311995
B18: EV / EBITDA | C18: =MIN('D. Trading Multiples'!D7,'D. Trading Multiples'!D9,'D. Trading Multiples'!D10) -> 4.1522388 | D18: =MEDIAN('D. Trading Multiples'!D7,'D. Trading Multiples'!D9,'D. Trading Multiples'!D10) -> 6.2325581 | E18: =MAX('D. Trading Multiples'!D7,'D. Trading Multiples'!D9,'D. Trading Multiples'!D10) -> 6.6530612
B20: Implied Valuation - EV/EBITDA Method (primary)
C21: Low | D21: Base | E21: High
B22: Implied Enterprise Value ($M) | C22: =C18*C6 -> 16766.74 | D22: =D18*C6 -> 25167.07 | E22: =E18*C6 -> 26865.061
B23: Less: Net Debt ($M) | C23: =C11 -> 5963 | D23: =C11 -> 5963 | E23: =C11 -> 5963
B24: Implied Equity Value ($M) | C24: =C22-C23 -> 10803.74 | D24: =D22-D23 -> 19204.07 | E24: =E22-E23 -> 20902.061
B25: Implied Value per Share | C25: =C24/C12 -> 11.813564 | D25: =D24/C12 -> 20.99907 | E25: =E24/C12 -> 22.855773
B26: Upside / (Downside) vs. Current Price | C26: =C25/C13-1 -> -0.48614338 | D26: =D25/C13-1 -> -0.086599813 | E26: =E25/C13-1 -> -0.0058385092
B28: Cross-Check - EV/Sales Method
C29: Low | D29: Base | E29: High
B30: Implied Enterprise Value ($M) | C30: =C17*C5 -> 10640.427 | D30: =D17*C5 -> 34407.982 | E30: =E17*C5 -> 54725.288
B31: Implied Equity Value ($M) | C31: =C30-C11 -> 4677.4273 | D31: =D30-C11 -> 28444.982 | E31: =E30-C11 -> 48762.288
B32: Implied Value per Share | C32: =C31/C12 -> 5.1146254 | D32: =D31/C12 -> 31.103728 | E32: =E31/C12 -> 53.320089
B34: Key Assumptions & Methodology
B35: - Primary valuation method is EV/EBITDA applied to HP's TTM EBITDA, using the Low/Median/High of the 'core' 3-comp peer set (Canon, Lenovo, Seiko Epson).
B36: - Dell and Xerox are excluded from the multiple basis for the reasons documented in the Benchmarking sheet (AI-driven re-rating; distressed/negative-equity profile) but are shown throughout for transparency.
B37: - EV/Sales is used as a cross-check given HP's below-peer-average EBITDA margin (7.0% vs. peer core-set range of ~4.5%-15.3%) - it implies a higher value than EV/EBITDA, consistent with HP trading cheap on a margin-adjusted basis versus Canon/Epson.
B38: - Net debt is held constant across Low/Base/High cases (capital structure assumed unchanged in the near term).
B39: - P/E-based valuation was not used as a primary method: peer P/E multiples are distorted by Dell's AI-server re-rating (~33x) and Epson's depressed current-year earnings (~50x), producing an unrealistically high implied value; see Trading Multiples and Benchmarking sheets.
B40: - All figures are as of Jul 7-8, 2026 market data; results will shift with subsequent earnings releases or market moves - refresh Financial Data sheet inputs periodically.
